slff/__init__.py
slff-0.0.3.dist-info/LICENSE.md
slff-0.0.3.dist-info/METADATA
slff-0.0.3.dist-info/WHEEL
slff-0.0.3.dist-info/top_level.txt
slff-0.0.3.dist-info/RECORD
